README.rst
setup.py
SQLAlchemy_JSON_API.egg-info/PKG-INFO
SQLAlchemy_JSON_API.egg-info/SOURCES.txt
SQLAlchemy_JSON_API.egg-info/dependency_links.txt
SQLAlchemy_JSON_API.egg-info/not-zip-safe
SQLAlchemy_JSON_API.egg-info/requires.txt
SQLAlchemy_JSON_API.egg-info/top_level.txt
sqlalchemy_json_api/__init__.py
sqlalchemy_json_api/exc.py
sqlalchemy_json_api/hybrids.py
sqlalchemy_json_api/query_builder.py
sqlalchemy_json_api/utils.py
sqlalchemy_json_api.egg-info/PKG-INFO
sqlalchemy_json_api.egg-info/SOURCES.txt
sqlalchemy_json_api.egg-info/dependency_links.txt
sqlalchemy_json_api.egg-info/not-zip-safe
sqlalchemy_json_api.egg-info/requires.txt
sqlalchemy_json_api.egg-info/top_level.txt
tests/__init__.py
tests/conftest.py
tests/test_select.py
tests/test_select_one.py
tests/test_select_related.py
tests/test_select_relationship.py
tests/test_select_with_include.py
tests/test_select_with_links.py
tests/test_select_with_sort.py
tests/test_type_formatters.py
tests/test_utils.py